[{"text": "para qu\u00e9 sirve tambi\u00e9n son las que", "start": 0.0, "duration": 3.689}, {"text": "inter\u00e9s globales pensando en el tema del", "start": 1.5, "duration": 4.819}, {"text": "curso", "start": 3.689, "duration": 2.63}, {"text": "d podemos hacer a una imagen de otra", "start": 6.859, "duration": 4.95}, {"text": "imagen podemos calcular la distancia", "start": 10.43, "duration": 3.869}, {"text": "entre ellas y en la distancia entre", "start": 11.809, "duration": 4.771}, {"text": "ellas", "start": 14.299, "duration": 3.771}, {"text": "puede ser un descriptor global se", "start": 16.58, "duration": 4.14}, {"text": "calcula un descriptor global y distancia", "start": 18.07, "duration": 4.15}, {"text": "entre los descriptores pero cuando como", "start": 20.72, "duration": 4.799}, {"text": "lo hacemos con escritores locales", "start": 22.22, "duration": 6.42}, {"text": "de alguna forma podr\u00eda ser uno dir\u00eda", "start": 25.519, "duration": 6.141}, {"text": "abro el n\u00famero de inline years", "start": 28.64, "duration": 5.66}, {"text": "de la transformaci\u00f3n geom\u00e9trica que", "start": 31.66, "duration": 5.25}, {"text": "encontramos nos dice que tanto se parece", "start": 34.3, "duration": 4.29}, {"text": "a lo que est\u00e1 seguro estamos de que hay", "start": 36.91, "duration": 4.35}, {"text": "m\u00e1gico entonces podr\u00edamos decir s\u00ed que", "start": 38.59, "duration": 6.93}, {"text": "al \u00faltimo 50 es lines entonces se parece", "start": 41.26, "duration": 5.82}, {"text": "mucho ya como la similitud entre grande", "start": 45.52, "duration": 4.499}, {"text": "im\u00e1genes y lo podemos convertir as\u00ed", "start": 47.08, "duration": 6.54}, {"text": "informa bien live a distancia 1 - y el", "start": 50.019, "duration": 6.381}, {"text": "porcentaje con respecto al total", "start": 53.62, "duration": 5.61}, {"text": "entonces si siempre si aqu\u00ed hab\u00eda un 50", "start": 56.4, "duration": 6.33}, {"text": "desde anoche 50 de 80", "start": 59.23, "duration": 6.06}, {"text": "est\u00e1 s\u00faper seguro porque m\u00e1s de la mitad", "start": 62.73, "duration": 5.77}, {"text": "son players y 11 entonces tuvo un", "start": 65.29, "duration": 7.189}, {"text": "porcentaje y 1 - eso nos da la distancia", "start": 68.5, "duration": 3.979}, {"text": "esta es mi distancia y la voy a usar", "start": 72.69, "duration": 4.78}, {"text": "para buscar im\u00e1genes parec\u00eda entonces en", "start": 75.16, "duration": 4.23}, {"text": "mi mam\u00e1 ser la de quien el bosco", "start": 77.47, "duration": 4.11}, {"text": "cualquier est\u00e1 distancia no cumple la", "start": 79.39, "duration": 4.05}, {"text": "desigualdad regular ya seguro que no la", "start": 81.58, "duration": 6.39}, {"text": "cumple y porque uno puede saber eso sin", "start": 83.44, "duration": 7.41}, {"text": "tener que probarlo porque esto esto es", "start": 87.97, "duration": 6.3}, {"text": "tiene similitud parcial porque porque s\u00e9", "start": 90.85, "duration": 5.07}, {"text": "que hay un objeto", "start": 94.27, "duration": 4.56}, {"text": "y entre estos 200 hasta aqu\u00ed aunque", "start": 95.92, "duration": 4.7}, {"text": "tenemos", "start": 98.83, "duration": 3.09}, {"text": "[M\u00fasica]", "start": 100.62, "duration": 3.35}, {"text": "interesante esto para ver lo que las", "start": 101.92, "duration": 2.88}, {"text": "propiedades m\u00e1gicas", "start": 103.97, "duration": 1.96}, {"text": "[M\u00fasica]", "start": 104.8, "duration": 4.7}, {"text": "igual que tenemos una imagen y tenemos 2", "start": 105.93, "duration": 6.59}, {"text": "[M\u00fasica]", "start": 109.5, "duration": 5.76}, {"text": "entonces aqu\u00ed esperamos unir y aqu\u00ed de", "start": 112.52, "duration": 3.81}, {"text": "una imagen", "start": 115.26, "duration": 4.26}, {"text": "donde aparece el objeto es el tri\u00e1ngulo", "start": 116.33, "duration": 4.44}, {"text": "hasta", "start": 119.52, "duration": 3.95}, {"text": "entonces se ve que aqu\u00ed van a coincidir", "start": 120.77, "duration": 5.25}, {"text": "varios escritores", "start": 123.47, "duration": 5.53}, {"text": "y que va a estar a cierta distancia", "start": 126.02, "duration": 5.08}, {"text": "entonces se calcula una distancia de", "start": 129.0, "duration": 5.63}, {"text": "esta distancia", "start": 131.1, "duration": 3.53}, {"text": "y ah\u00ed est\u00e1 que la imagen o no y aqu\u00ed", "start": 136.48, "duration": 7.19}, {"text": "vamos a tener otro punto que va a estar", "start": 138.489, "duration": 5.181}, {"text": "05 y aqu\u00ed vamos tener otro punto", "start": 145.7, "duration": 5.159}, {"text": "digamos que estas citas", "start": 150.95, "duration": 4.23}, {"text": "pero no por qu\u00e9 por qu\u00e9 est\u00e1n tan de", "start": 155.33, "duration": 6.15}, {"text": "aqu\u00ed tenemos otra imagen", "start": 158.42, "duration": 7.16}, {"text": "d\u00f3nde est\u00e1s", "start": 161.48, "duration": 4.1}, {"text": "entonces tambi\u00e9n est\u00e1n cerca porque", "start": 168.79, "duration": 7.759}, {"text": "coinciden bien digamos tambi\u00e9n a 0", "start": 171.9, "duration": 4.649}, {"text": "cada planta y \u00e9ste y \u00e9ste no se van a", "start": 178.95, "duration": 4.44}, {"text": "aparecer de una", "start": 181.72, "duration": 4.72}, {"text": "la distancia entre este y este es", "start": 183.39, "duration": 5.929}, {"text": "un n\u00famero grande", "start": 186.44, "duration": 5.879}, {"text": "porque", "start": 189.319, "duration": 3.0}, {"text": "digamos 1", "start": 193.61, "duration": 3.209}, {"text": "algunas", "start": 198.25, "duration": 4.8}, {"text": "de la distancia en", "start": 199.96, "duration": 7.03}, {"text": "esta imagen la distancia 1 pero cada una", "start": 203.05, "duration": 7.74}, {"text": "esta distancia 0 1 0 1 1 2", "start": 206.99, "duration": 8.84}, {"text": "[M\u00fasica]", "start": 210.79, "duration": 5.04}, {"text": "como un objeto de estar cerca de 2 2 y", "start": 216.58, "duration": 6.72}, {"text": "eso se cumpli\u00f3 por la desigualdad", "start": 220.94, "duration": 5.01}, {"text": "por la similitud parcial", "start": 223.3, "duration": 4.46}, {"text": "bueno", "start": 225.95, "duration": 5.14}, {"text": "porque entonces todo no es m\u00e9dica y de", "start": 227.76, "duration": 5.28}, {"text": "hecho hay otras formas y lo lleva a las", "start": 231.09, "duration": 3.239}, {"text": "siguientes clases como calcular un", "start": 233.04, "duration": 3.24}, {"text": "descriptor global pasando de escritores", "start": 234.329, "duration": 6.11}, {"text": "locales y encima cumplimiento pluvial", "start": 236.28, "duration": 4.159}]